icgc/__init__.py
icgc-0.1.3.dist-info/DESCRIPTION.rst
icgc-0.1.3.dist-info/METADATA
icgc-0.1.3.dist-info/RECORD
icgc-0.1.3.dist-info/WHEEL
icgc-0.1.3.dist-info/metadata.json
icgc-0.1.3.dist-info/top_level.txt
