Metadata-Version: 2.0
Name: icgc
Version: 0.1.3
Summary: A Python library interface to the International Cancer Genome Consortium's Web Portal
Home-page: https://github.com/icgc-dcc/icgc-python
Author: Kevin Hartmann
Author-email: Kevin.Hartmann@oicr.on.ca
License: License :: OSI Approved :: GNU General Public License v3 (GPLv3)
Keywords: icgc rest-client web-portal
Platform: UNKNOWN
Classifier: Development Status :: 3 - Alpha
Classifier: Intended Audience :: Developers
Classifier: License :: OSI Approved :: GNU General Public License v3 (GPLv3)
Classifier: Programming Language :: Python :: 2
Classifier: Programming Language :: Python :: 3
Requires-Dist: requests
